schemagic_boo/__init__.py
schemagic_boo/core.py
schemagic_boo-0.1.0.dist-info/licenses/LICENSE
schemagic_boo-0.1.0.dist-info/METADATA
schemagic_boo-0.1.0.dist-info/WHEEL
schemagic_boo-0.1.0.dist-info/entry_points.txt
schemagic_boo-0.1.0.dist-info/top_level.txt
schemagic_boo-0.1.0.dist-info/RECORD
